examples/fake_ifconfig.py
examples/list.py
orbuculum_bad/__init__.py
orbuculum_bad/cli.py
orbuculum_bad/protos/__init__.py
orbuculum_bad/protos/network.py
python_orbuculum_bad-0.1.3.dist-info/METADATA
python_orbuculum_bad-0.1.3.dist-info/WHEEL
python_orbuculum_bad-0.1.3.dist-info/entry_points.txt
python_orbuculum_bad-0.1.3.dist-info/RECORD
