Metadata-Version: 2.1
Name: python-orbuculum-bad
Version: 0.1.3
Summary: A really solo and ungly client for orbuculum service.
Author-email: ssfdust <ssfdust@gmail.com>
License: MIT
Requires-Python: >=3.7
Requires-Dist: grpc-requests~=0.1.10
